{"stats":{"minecraft:killed":{"minecraft:zombified_piglin":2,"minecraft:pig":1,"minecraft:piglin_brute":18,"minecraft:piglin":52,"minecraft:vindicator":21,"minecraft:ravager":3,"minecraft:silverfish":19,"minecraft:zombie":216,"minecraft:glow_squid":1,"minecraft:zombie_villager":8,"minecraft:chicken":8,"minecraft:drowned":1,"minecraft:cow":5,"minecraft:endermite":2,"minecraft:pillager":38,"minecraft:skeleton":73,"minecraft:phantom":61,"minecraft:iron_golem":13,"minecraft:witch":9,"minecraft:villager":1,"minecraft:spider":60,"minecraft:strider":1,"minecraft:horse":1,"minecraft:bogged":8,"minecraft:wither_skeleton":3,"minecraft:creeper":32,"minecraft:hoglin":3,"minecraft:sheep":9,"minecraft:enderman":18,"minecraft:evoker":6,"minecraft:magma_cube":44,"minecraft:vex":4,"minecraft:ghast":4,"minecraft:breeze":8,"minecraft:blaze":19},"minecraft:picked_up":{"minecraft:enchanting_table":1,"minecraft:cobblestone":470,"minecraft:shears":3,"minecraft:minecart":1,"minecraft:saddle":2,"minecraft:sugar_cane":112,"minecraft:bone":155,"minecraft:gold_ore":4,"minecraft:cooked_mutton":4,"minecraft:white_banner":2,"minecraft:blaze_rod":36,"minecraft:emerald":314,"minecraft:chainmail_chestplate":6,"minecraft:book":50,"minecraft:armor_stand":1,"minecraft:chainmail_helmet":2,"minecraft:bow":1,"minecraft:arrow":96,"minecraft:stone_shovel":6,"minecraft:iron_ingot":125,"minecraft:lilac":1,"minecraft:blue_banner":1,"minecraft:acacia_wood":33,"minecraft:crossbow":4,"minecraft:heavy_core":2,"minecraft:dandelion":2,"minecraft:mutton":1,"minecraft:golden_carrot":61,"minecraft:diamond_leggings":1,"minecraft:polished_blackstone_bricks":262,"minecraft:crimson_nylium":7,"minecraft:crimson_stem":30,"minecraft:deepslate_emerald_ore":1,"minecraft:cartography_table":4,"minecraft:oak_log":1101,"minecraft:lingering_potion":1,"minecraft:sand":366,"minecraft:wheat_seeds":111,"minecraft:oak_door":2,"minecraft:quartz":64,"minecraft:diamond_sword":3,"minecraft:red_bed":2,"minecraft:brown_bed":3,"minecraft:blast_furnace":1,"minecraft:loom":1,"minecraft:chainmail_boots":5,"minecraft:green_bed":8,"minecraft:music_disc_pigstep":3,"minecraft:ender_pearl":236,"minecraft:string":159,"minecraft:golden_sword":1,"minecraft:smithing_table":3,"minecraft:stone_bricks":4,"minecraft:obsidian":41,"minecraft:leather_boots":2,"minecraft:white_carpet":11,"minecraft:nether_wart_block":4,"minecraft:ender_chest":123,"minecraft:acacia_trapdoor":4,"minecraft:enchanted_book":15,"minecraft:experience_bottle":298,"minecraft:iron_block":15,"minecraft:tripwire_hook":36,"minecraft:yellow_terracotta":4,"minecraft:glowstone":5,"minecraft:white_bed":8,"minecraft:stripped_oak_log":6,"minecraft:guster_banner_pattern":1,"minecraft:warped_trapdoor":5,"minecraft:brown_mushroom":6,"minecraft:wooden_axe":1,"minecraft:armadillo_scute":42,"minecraft:music_disc_tears":3,"minecraft:prismarine":38,"minecraft:lightning_rod":8,"minecraft:stick":675,"minecraft:redstone_torch":1,"minecraft:polished_tuff":1,"minecraft:bamboo":192,"minecraft:deepslate_redstone_ore":2,"minecraft:diamond_boots":5,"minecraft:cooked_porkchop":3,"minecraft:iron_axe":11,"minecraft:deepslate":568,"minecraft:cookie":257,"minecraft:raw_iron":4,"minecraft:diamond_chestplate":4,"minecraft:netherite_leggings":1,"minecraft:leather_helmet":1,"minecraft:chest":9,"minecraft:lectern":213,"minecraft:netherite_sword":6,"minecraft:cobbled_deepslate_slab":1,"minecraft:netherrack":1447,"minecraft:netherite_block":1,"minecraft:crimson_planks":50,"minecraft:trident":1,"minecraft:stone":246,"minecraft:gravel":43,"minecraft:jungle_planks":97,"minecraft:jungle_boat":3,"minecraft:tuff":21,"minecraft:phantom_membrane":5,"minecraft:shield":36,"minecraft:lapis_lazuli":9,"minecraft:crimson_trapdoor":2,"minecraft:jungle_log":4896,"minecraft:ominous_bottle":7,"minecraft:trial_key":1,"minecraft:black_banner":1,"minecraft:waxed_oxidized_cut_copper_stairs":1,"minecraft:oak_boat":8,"minecraft:cobweb":78,"minecraft:oak_planks":7,"minecraft:flint_and_steel":2,"minecraft:netherite_chestplate":4,"minecraft:raw_copper":46,"minecraft:rotten_flesh":37387,"minecraft:acacia_fence":36,"minecraft:fermented_spider_eye":24,"minecraft:ancient_debris":19,"minecraft:apple":6,"minecraft:jukebox":1,"minecraft:orange_glazed_terracotta":1,"minecraft:smooth_sandstone":2,"minecraft:crimson_slab":1,"minecraft:orange_bed":20,"minecraft:melon":572,"minecraft:iron_door":2,"minecraft:brewing_stand":19,"minecraft:composter":11,"minecraft:flint":18,"minecraft:redstone":192,"minecraft:deepslate_tiles":6,"minecraft:flow_banner_pattern":1,"minecraft:orange_terracotta":2,"minecraft:firefly_bush":1,"minecraft:melon_slice":64,"minecraft:diamond":29,"minecraft:granite":87,"minecraft:crimson_roots":1,"minecraft:flow_armor_trim_smithing_template":2,"minecraft:nether_wart":293,"minecraft:cobbled_deepslate_stairs":1,"minecraft:gold_block":246,"minecraft:magma_cream":23,"minecraft:end_stone":32,"minecraft:enchanted_golden_apple":5,"minecraft:hay_block":166,"minecraft:polished_blackstone_brick_stairs":2,"minecraft:stone_sword":1,"minecraft:acacia_log":250,"minecraft:emerald_block":13,"minecraft:deepslate_bricks":2,"minecraft:mossy_stone_bricks":3,"minecraft:acacia_planks":47,"minecraft:lime_bed":11,"minecraft:dirt":319,"minecraft:basalt":177,"minecraft:rail":3,"minecraft:diamond_helmet":2,"minecraft:torch":26,"minecraft:diamond_pickaxe":1,"minecraft:silence_armor_trim_smithing_template":1,"minecraft:ender_eye":2,"minecraft:bread":162,"minecraft:iron_boots":1,"minecraft:spruce_log":3,"minecraft:coal":30,"minecraft:acacia_boat":38,"minecraft:netherite_pickaxe":1,"minecraft:splash_potion":826,"minecraft:iron_pickaxe":1,"minecraft:tnt":9,"minecraft:weeping_vines":1,"minecraft:golden_axe":8,"minecraft:bookshelf":4,"minecraft:hopper":3,"minecraft:totem_of_undying":25,"minecraft:poppy":31,"minecraft:stone_hoe":7,"minecraft:cooked_beef":8,"minecraft:potion":1333,"minecraft:fletching_table":19,"minecraft:andesite":13,"minecraft:diamond_hoe":1,"minecraft:sandstone":120,"minecraft:stone_pressure_plate":1,"minecraft:coal_ore":2,"minecraft:soul_sand":22,"minecraft:diamond_axe":4,"minecraft:soul_soil":1,"minecraft:breeze_rod":67,"minecraft:cracked_polished_blackstone_bricks":36,"minecraft:netherite_boots":2,"minecraft:water_bucket":3,"minecraft:stone_pickaxe":4,"minecraft:gold_ingot":7,"minecraft:baked_potato":4,"minecraft:melon_seeds":2,"minecraft:coast_armor_trim_smithing_template":1,"minecraft:oak_leaves":1,"minecraft:golden_apple":109,"minecraft:oak_trapdoor":2,"minecraft:prismarine_bricks":5,"minecraft:acacia_slab":20,"minecraft:leather_chestplate":2,"minecraft:golden_chestplate":1,"minecraft:acacia_leaves":1,"minecraft:grindstone":5,"minecraft:kelp":40,"minecraft:cobbled_deepslate":701,"minecraft:acacia_stairs":2,"minecraft:cyan_bed":11,"minecraft:glowstone_dust":42,"minecraft:pumpkin_seeds":1,"minecraft:stone_axe":4,"minecraft:jungle_sapling":218,"minecraft:wheat":6,"minecraft:tuff_bricks":5,"minecraft:map":8,"minecraft:damaged_anvil":1,"minecraft:gunpowder":19,"minecraft:pumpkin_pie":15,"minecraft:netherite_helmet":2,"minecraft:nether_gold_ore":24,"minecraft:blackstone":50,"minecraft:blaze_powder":3,"minecraft:chainmail_leggings":5,"minecraft:lever":4,"minecraft:leaf_litter":48,"minecraft:nether_brick_fence":6,"minecraft:deepslate_gold_ore":3,"minecraft:grass_block":1,"minecraft:birch_log":7,"minecraft:music_disc_creator":2,"minecraft:pumpkin":2911,"minecraft:spider_eye":97,"minecraft:bone_meal":11,"minecraft:netherite_axe":1,"minecraft:tipped_arrow":21,"minecraft:diorite":10,"minecraft:wet_sponge":2,"minecraft:crafting_table":21,"minecraft:ominous_trial_key":4,"minecraft:oak_sapling":54,"minecraft:bundle":5,"minecraft:polished_deepslate_stairs":24,"minecraft:cake":1,"minecraft:wind_charge":345,"minecraft:cobblestone_slab":12,"minecraft:jungle_leaves":16,"minecraft:netherite_ingot":1,"minecraft:dried_ghast":53,"minecraft:paper":7},"minecraft:crafted":{"minecraft:wooden_axe":2,"minecraft:wind_charge":472,"minecraft:arrow":64,"minecraft:gold_ingot":4419,"minecraft:crimson_planks":108,"minecraft:cookie":498,"minecraft:netherite_sword":1,"minecraft:lever":1,"minecraft:mangrove_log":32,"minecraft:diamond_pickaxe":1,"minecraft:chest":33,"minecraft:iron_block":20,"minecraft:bookshelf":30,"minecraft:ender_pearl":466,"minecraft:acacia_planks":2448,"minecraft:bucket":5,"minecraft:flint_and_steel":1,"minecraft:jungle_planks":32016,"minecraft:ladder":3,"minecraft:glass":362,"minecraft:cobblestone_slab":60,"minecraft:mangrove_planks":128,"minecraft:oak_trapdoor":2,"minecraft:brewing_stand":7,"minecraft:cobbled_deepslate_slab":6,"minecraft:sugar":25,"minecraft:cobbled_deepslate_stairs":4,"minecraft:netherite_upgrade_smithing_template":12,"minecraft:iron_door":3,"minecraft:acacia_trapdoor":14,"minecraft:smooth_stone":3,"minecraft:crimson_slab":12,"minecraft:cooked_beef":5,"minecraft:oak_slab":6,"minecraft:golden_carrot":537,"minecraft:fletching_table":7,"minecraft:netherite_axe":1,"minecraft:wooden_shovel":1,"minecraft:apple":300,"minecraft:paper":48,"minecraft:armor_stand":1,"minecraft:acacia_boat":8,"minecraft:iron_ingot":96,"minecraft:diamond_helmet":2,"minecraft:tripwire_hook":2,"minecraft:stone":0,"minecraft:blaze_powder":48,"minecraft:acacia_slab":108,"minecraft:experience_bottle":937,"minecraft:diamond_leggings":1,"minecraft:enchanted_book":31,"minecraft:shield":7,"minecraft:netherite_pickaxe":1,"minecraft:iron_axe":1,"minecraft:tipped_arrow":60,"minecraft:golden_apple":437,"minecraft:diamond_boots":1,"minecraft:ender_eye":3,"minecraft:acacia_stairs":4,"minecraft:stick":76664,"minecraft:smooth_stone_slab":6,"minecraft:ender_chest":3,"minecraft:diamond_axe":2,"minecraft:lightning_rod":1,"minecraft:jungle_slab":6,"minecraft:air":0,"minecraft:jungle_trapdoor":2,"minecraft:redstone":164,"minecraft:bone_meal":477,"minecraft:oak_boat":3,"minecraft:glass_bottle":360,"minecraft:acacia_fence":21,"minecraft:lapis_lazuli":12,"minecraft:oak_planks":4412,"minecraft:shears":2,"minecraft:iron_shovel":2,"minecraft:polished_deepslate":12,"minecraft:polished_deepslate_stairs":8,"minecraft:birch_planks":28,"minecraft:jungle_stairs":4,"minecraft:crimson_trapdoor":6,"minecraft:anvil":5,"minecraft:netherite_ingot":5,"minecraft:emerald_block":60,"minecraft:wooden_pickaxe":1,"minecraft:glowstone":18,"minecraft:diamond_chestplate":1,"minecraft:diamond_sword":1,"minecraft:emerald":4984,"minecraft:netherite_scrap":21,"minecraft:wheat":1035,"minecraft:gold_block":129,"minecraft:white_carpet":3,"minecraft:bread":625,"minecraft:crafting_table":40,"minecraft:torch":56,"minecraft:white_bed":2,"minecraft:jungle_log":32,"minecraft:lectern":14,"minecraft:iron_pickaxe":1},"minecraft:broken":{"minecraft:wooden_axe":1,"minecraft:iron_shovel":2,"minecraft:bow":1,"minecraft:wooden_shovel":1},"minecraft:custom":{"minecraft:eat_cake_slice":3,"minecraft:talked_to_villager":1767,"minecraft:time_since_rest":1397792,"minecraft:leave_game":113,"minecraft:damage_taken":44842,"minecraft:mob_kills":824,"minecraft:boat_one_cm":573377,"minecraft:damage_absorbed":8379,"minecraft:time_since_death":2652333,"minecraft:open_enderchest":351,"minecraft:damage_dealt_absorbed":8987,"minecraft:interact_with_brewingstand":655,"minecraft:interact_with_furnace":344,"minecraft:interact_with_smithing_table":12,"minecraft:sleep_in_bed":33,"minecraft:inspect_dispenser":11,"minecraft:happy_ghast_one_cm":334112,"minecraft:swim_one_cm":294182,"minecraft:total_world_time":2696636,"minecraft:crouch_one_cm":225695,"minecraft:raid_win":2,"minecraft:climb_one_cm":15709,"minecraft:deaths":3,"minecraft:player_kills":9,"minecraft:traded_with_villager":5694,"minecraft:damage_resisted":2826,"minecraft:damage_blocked_by_shield":73702,"minecraft:interact_with_crafting_table":210,"minecraft:walk_one_cm":2281316,"minecraft:walk_under_water_one_cm":56478,"minecraft:damage_dealt":194295,"minecraft:play_time":2696636,"minecraft:jump":65531,"minecraft:play_record":2,"minecraft:drop":3411,"minecraft:bell_ring":6,"minecraft:open_barrel":76,"minecraft:sprint_one_cm":9018218,"minecraft:open_chest":3327,"minecraft:inspect_hopper":55,"minecraft:fall_one_cm":2022382,"minecraft:fly_one_cm":15668614,"minecraft:interact_with_anvil":101,"minecraft:walk_on_water_one_cm":156192,"minecraft:sneak_time":102608,"minecraft:raid_trigger":1,"minecraft:interact_with_blast_furnace":11,"minecraft:interact_with_grindstone":8},"minecraft:dropped":{"minecraft:soul_soil":1,"minecraft:oak_leaves":1,"minecraft:music_disc_tears":1,"minecraft:cracked_polished_blackstone_bricks":34,"minecraft:flow_banner_pattern":1,"minecraft:brewing_stand":2,"minecraft:smooth_stone_slab":5,"minecraft:netherite_helmet":1,"minecraft:gravel":8,"minecraft:bone":54,"minecraft:netherite_chestplate":2,"minecraft:poppy":11,"minecraft:glowstone":4,"minecraft:cobweb":98,"minecraft:grindstone":1,"minecraft:cobblestone_slab":10,"minecraft:breeze_rod":23,"minecraft:blackstone":11,"minecraft:tuff_bricks":5,"minecraft:enchanted_book":8,"minecraft:pumpkin":4,"minecraft:crossbow":6,"minecraft:oak_sapling":4,"minecraft:prismarine":1,"minecraft:emerald_block":80,"minecraft:leather_chestplate":2,"minecraft:lilac":1,"minecraft:redstone":169,"minecraft:jungle_sapling":5,"minecraft:grass_block":1,"minecraft:golden_carrot":106,"minecraft:tuff":2,"minecraft:book":2,"minecraft:netherite_leggings":1,"minecraft:arrow":160,"minecraft:white_bed":1,"minecraft:gunpowder":12,"minecraft:deepslate":304,"minecraft:gold_ingot":4,"minecraft:enchanted_golden_apple":2,"minecraft:stone_axe":3,"minecraft:guster_banner_pattern":1,"minecraft:cooked_mutton":4,"minecraft:baked_potato":4,"minecraft:diorite":1,"minecraft:golden_apple":225,"minecraft:tipped_arrow":18,"minecraft:rotten_flesh":3053,"minecraft:stone_shovel":3,"minecraft:chainmail_leggings":4,"minecraft:iron_helmet":1,"minecraft:sandstone":1,"minecraft:stone_sword":1,"minecraft:bow":2,"minecraft:end_stone":24,"minecraft:jungle_leaves":6,"minecraft:ender_eye":1,"minecraft:bucket":1,"minecraft:dirt":15,"minecraft:dune_armor_trim_smithing_template":1,"minecraft:stone":75,"minecraft:crimson_planks":15,"minecraft:obsidian":6,"minecraft:melon_slice":15,"minecraft:shears":3,"minecraft:ender_chest":7,"minecraft:wet_sponge":2,"minecraft:ender_pearl":258,"minecraft:music_disc_creator":1,"minecraft:nether_brick_fence":6,"minecraft:emerald":409,"minecraft:rail":1,"minecraft:coal":6,"minecraft:glass_bottle":2,"minecraft:acacia_leaves":1,"minecraft:bamboo":192,"minecraft:green_bed":2,"minecraft:cooked_beef":2,"minecraft:iron_block":11,"minecraft:stone_hoe":6,"minecraft:netherite_axe":1,"minecraft:acacia_fence":3,"minecraft:cookie":575,"minecraft:crafting_table":1,"minecraft:jungle_planks":10,"minecraft:golden_helmet":2,"minecraft:lapis_lazuli":14,"minecraft:fermented_spider_eye":18,"minecraft:netherrack":576,"minecraft:netherite_block":1,"minecraft:mutton":1,"minecraft:cooked_porkchop":3,"minecraft:white_banner":2,"minecraft:iron_axe":9,"minecraft:oak_planks":21,"minecraft:wheat":1,"minecraft:basalt":31,"minecraft:chainmail_helmet":2,"minecraft:experience_bottle":446,"minecraft:cobbled_deepslate":67,"minecraft:armadillo_scute":1,"minecraft:wheat_seeds":57,"minecraft:iron_ingot":90,"minecraft:flint_and_steel":1,"minecraft:yellow_terracotta":3,"minecraft:paper":4,"minecraft:composter":3,"minecraft:stone_pickaxe":3,"minecraft:trident":1,"minecraft:shield":33,"minecraft:netherite_ingot":1,"minecraft:chainmail_chestplate":6,"minecraft:jungle_boat":1,"minecraft:flow_armor_trim_smithing_template":2,"minecraft:polished_tuff":1,"minecraft:oak_log":7,"minecraft:acacia_slab":1,"minecraft:diamond_pickaxe":1,"minecraft:string":84,"minecraft:polished_blackstone_bricks":157,"minecraft:blaze_powder":4,"minecraft:stick":778,"minecraft:coal_ore":2,"minecraft:phantom_membrane":5,"minecraft:bread":855,"minecraft:spider_eye":32,"minecraft:netherite_boots":1,"minecraft:iron_boots":1,"minecraft:diamond_hoe":1,"minecraft:mossy_stone_bricks":3,"minecraft:leather_helmet":1,"minecraft:totem_of_undying":27,"minecraft:melon_seeds":2,"minecraft:cobblestone":196,"minecraft:nether_wart_block":2,"minecraft:leather_boots":2,"minecraft:jungle_log":288,"minecraft:wind_charge":53,"minecraft:diamond_axe":3,"minecraft:dried_ghast":40,"minecraft:golden_axe":7,"minecraft:potion":1017,"minecraft:bundle":5,"minecraft:diamond_helmet":3,"minecraft:iron_hoe":1,"minecraft:diamond_boots":4,"minecraft:diamond_chestplate":4,"minecraft:gold_block":64,"minecraft:diamond_leggings":1,"minecraft:splash_potion":866,"minecraft:quartz":64,"minecraft:chainmail_boots":5,"minecraft:granite":23,"minecraft:saddle":2,"minecraft:diamond":27,"minecraft:golden_sword":1,"minecraft:bone_meal":3,"minecraft:pumpkin_pie":9,"minecraft:crying_obsidian":3,"minecraft:jungle_stairs":1,"minecraft:map":7,"minecraft:netherite_sword":8,"minecraft:stone_bricks":4,"minecraft:leaf_litter":7,"minecraft:diamond_sword":3,"minecraft:lingering_potion":4,"minecraft:magma_cream":4},"minecraft:killed_by":{"minecraft:skeleton":2,"minecraft:player":1},"minecraft:mined":{"minecraft:spruce_log":4,"minecraft:nether_quartz_ore":29,"minecraft:chest":9,"minecraft:smooth_sandstone":2,"minecraft:pumpkin":2923,"minecraft:netherrack":6980,"minecraft:waxed_oxidized_cut_copper_stairs":1,"minecraft:brown_bed":3,"minecraft:weeping_vines_plant":1,"minecraft:brown_mushroom":7,"minecraft:attached_pumpkin_stem":1,"minecraft:birch_log":7,"minecraft:blue_banner":1,"minecraft:jungle_sapling":8,"minecraft:magma_block":20,"minecraft:obsidian":21,"minecraft:waxed_oxidized_copper":1,"minecraft:tnt":9,"minecraft:waxed_weathered_copper_bulb":1,"minecraft:sandstone":126,"minecraft:melon":543,"minecraft:stripped_spruce_log":7,"minecraft:blackstone":145,"minecraft:grindstone":4,"minecraft:nether_wart_block":4,"minecraft:deepslate_bricks":2,"minecraft:iron_door":6,"minecraft:birch_leaves":2,"minecraft:jungle_planks":6,"minecraft:gold_block":115,"minecraft:nether_brick_fence":2,"minecraft:wall_torch":14,"minecraft:decorated_pot":8,"minecraft:fern":20,"minecraft:fire":23,"minecraft:kelp_plant":1,"minecraft:smithing_table":3,"minecraft:ender_chest":112,"minecraft:deepslate_tiles":6,"minecraft:oak_sapling":3,"minecraft:iron_ore":5,"minecraft:acacia_log":247,"minecraft:oak_planks":8,"minecraft:cobblestone":119,"minecraft:sugar_cane":60,"minecraft:tripwire_hook":1,"minecraft:kelp":38,"minecraft:oak_leaves":185,"minecraft:orange_glazed_terracotta":1,"minecraft:brewing_stand":19,"minecraft:yellow_terracotta":2,"minecraft:crimson_slab":1,"minecraft:cyan_bed":8,"minecraft:rose_bush":1,"minecraft:fletching_table":20,"minecraft:deepslate_copper_ore":3,"minecraft:black_banner":1,"minecraft:crimson_roots":1,"minecraft:cracked_stone_bricks":5,"minecraft:tall_grass":31,"minecraft:cartography_table":4,"minecraft:mossy_stone_bricks":6,"minecraft:tall_seagrass":2,"minecraft:rail":3,"minecraft:cobbled_deepslate_slab":1,"minecraft:dirt":108,"minecraft:acacia_trapdoor":4,"minecraft:acacia_slab":15,"minecraft:tripwire":5,"minecraft:hopper":3,"minecraft:soul_fire":2,"minecraft:basalt":538,"minecraft:sand":359,"minecraft:deepslate":1211,"minecraft:seagrass":1,"minecraft:orange_bed":20,"minecraft:oak_log":1102,"minecraft:oak_door":2,"minecraft:red_bed":2,"minecraft:spawner":1,"minecraft:acacia_fence":35,"minecraft:lime_bed":6,"minecraft:vine":109,"minecraft:warped_nylium":3,"minecraft:polished_blackstone_brick_stairs":3,"minecraft:lectern":213,"minecraft:chiseled_polished_blackstone":2,"minecraft:weeping_vines":4,"minecraft:gravel":39,"minecraft:short_grass":314,"minecraft:waxed_copper_grate":4,"minecraft:red_mushroom":1,"minecraft:infested_stone_bricks":1,"minecraft:acacia_leaves":3,"minecraft:loom":1,"minecraft:prismarine_bricks":5,"minecraft:cracked_polished_blackstone_bricks":64,"minecraft:crafting_table":18,"minecraft:deepslate_redstone_ore":2,"minecraft:leaf_litter":13,"minecraft:stripped_oak_log":7,"minecraft:lilac":1,"minecraft:jungle_log":3685,"minecraft:copper_ore":10,"minecraft:firefly_bush":1,"minecraft:gold_ore":4,"minecraft:andesite":46,"minecraft:packed_ice":3,"minecraft:glowstone":15,"minecraft:blast_furnace":1,"minecraft:deepslate_gold_ore":3,"minecraft:ice":1,"minecraft:nether_bricks":5,"minecraft:poppy":3,"minecraft:deepslate_iron_ore":1,"minecraft:green_bed":5,"minecraft:jungle_leaves":297,"minecraft:warped_trapdoor":5,"minecraft:stone":705,"minecraft:stone_bricks":13,"minecraft:heavy_core":1,"minecraft:orange_terracotta":2,"minecraft:granite":125,"minecraft:bush":3,"minecraft:crimson_stem":32,"minecraft:coal_ore":22,"minecraft:diorite":37,"minecraft:wheat":2,"minecraft:ancient_debris":19,"minecraft:hay_block":116,"minecraft:crimson_trapdoor":2,"minecraft:oak_trapdoor":2,"minecraft:dried_ghast":11,"minecraft:white_bed":8,"minecraft:prismarine":37,"minecraft:polished_deepslate_stairs":24,"minecraft:composter":10,"minecraft:bookshelf":18,"minecraft:cobbled_deepslate_stairs":5,"minecraft:soul_sand":30,"minecraft:white_carpet":6,"minecraft:short_dry_grass":3,"minecraft:stripped_jungle_log":3,"minecraft:crimson_nylium":32,"minecraft:soul_soil":3,"minecraft:gilded_blackstone":2,"minecraft:enchanting_table":1,"minecraft:polished_blackstone_bricks":308,"minecraft:nether_wart":122,"minecraft:grass_block":222,"minecraft:cobweb":41,"minecraft:spruce_leaves":1,"minecraft:chiseled_tuff_bricks":1,"minecraft:cobbled_deepslate":192,"minecraft:tuff":19,"minecraft:polished_tuff":1,"minecraft:tuff_bricks":9,"minecraft:cut_sandstone":4,"minecraft:damaged_anvil":1,"minecraft:nether_gold_ore":28,"minecraft:cobblestone_slab":12,"minecraft:jukebox":1,"minecraft:acacia_wood":33,"minecraft:redstone_wire":8,"minecraft:lightning_rod":8,"minecraft:stone_stairs":1,"minecraft:crimson_planks":32,"minecraft:acacia_planks":14},"minecraft:used":{"minecraft:acacia_boat":38,"minecraft:prismarine":37,"minecraft:iron_axe":5,"minecraft:end_stone":1,"minecraft:kelp":40,"minecraft:ominous_trial_key":4,"minecraft:cartography_table":2,"minecraft:melon":1,"minecraft:netherite_axe":6840,"minecraft:diamond_sword":378,"minecraft:cobbled_deepslate_slab":1,"minecraft:acacia_slab":50,"minecraft:black_banner":1,"minecraft:jungle_trapdoor":2,"minecraft:glass_bottle":404,"minecraft:wooden_axe":38,"minecraft:netherite_pickaxe":4859,"minecraft:granite":11,"minecraft:crimson_stem":1,"minecraft:iron_shovel":515,"minecraft:hay_block":6,"minecraft:damaged_anvil":4,"minecraft:jungle_log":18,"minecraft:smithing_table":2,"minecraft:oak_log":12,"minecraft:grindstone":3,"minecraft:diamond_axe":3278,"minecraft:white_carpet":14,"minecraft:nether_wart":113,"minecraft:poppy":2,"minecraft:jungle_boat":3,"minecraft:armor_stand":2,"minecraft:bow":5,"minecraft:oak_door":2,"minecraft:cobbled_deepslate_stairs":1,"minecraft:loom":1,"minecraft:cobbled_deepslate":234,"minecraft:acacia_planks":24,"minecraft:netherrack":699,"minecraft:lingering_potion":1,"minecraft:dried_ghast":13,"minecraft:lightning_rod":9,"minecraft:prismarine_bricks":5,"minecraft:bone_meal":490,"minecraft:fletching_table":26,"minecraft:glowstone":23,"minecraft:anvil":6,"minecraft:dirt":54,"minecraft:acacia_fence":53,"minecraft:obsidian":20,"minecraft:sand":26,"minecraft:wind_charge":723,"minecraft:orange_bed":20,"minecraft:basalt":146,"minecraft:rail":1,"minecraft:shears":6,"minecraft:lectern":226,"minecraft:bucket":481,"minecraft:splash_potion":216,"minecraft:deepslate_tiles":6,"minecraft:polished_blackstone_brick_stairs":2,"minecraft:enchanted_golden_apple":3,"minecraft:oak_planks":7,"minecraft:totem_of_undying":2,"minecraft:oak_sapling":28,"minecraft:brown_egg":1,"minecraft:sugar_cane":8,"minecraft:iron_door":2,"minecraft:trial_key":1,"minecraft:oak_trapdoor":4,"minecraft:string":14,"minecraft:netherite_sword":2611,"minecraft:shield":296,"minecraft:deepslate":242,"minecraft:iron_pickaxe":224,"minecraft:andesite":9,"minecraft:oak_boat":11,"minecraft:golden_carrot":536,"minecraft:acacia_log":2,"minecraft:deepslate_bricks":2,"minecraft:bookshelf":18,"minecraft:diamond_pickaxe":6255,"minecraft:crimson_planks":23,"minecraft:ladder":3,"minecraft:crossbow":1,"minecraft:jungle_stairs":3,"minecraft:tuff":18,"minecraft:crimson_slab":9,"minecraft:brewing_stand":22,"minecraft:lava_bucket":5,"minecraft:polished_deepslate_stairs":29,"minecraft:red_bed":2,"minecraft:diorite":9,"minecraft:ominous_bottle":2,"minecraft:redstone":28,"minecraft:tropical_fish_bucket":1,"minecraft:pumpkin_seeds":1,"minecraft:lime_bed":1,"minecraft:diamond_leggings":1,"minecraft:wooden_shovel":59,"minecraft:cobblestone":111,"minecraft:diamond_chestplate":1,"minecraft:stone":79,"minecraft:hopper":6,"minecraft:golden_apple":255,"minecraft:heavy_core":2,"minecraft:acacia_stairs":4,"minecraft:crafting_table":22,"minecraft:netherite_chestplate":2,"minecraft:potion":8,"minecraft:white_bed":10,"minecraft:diamond_boots":2,"minecraft:acacia_trapdoor":18,"minecraft:netherite_helmet":3,"minecraft:apple":45,"minecraft:orange_glazed_terracotta":1,"minecraft:crimson_trapdoor":8,"minecraft:pumpkin":1,"minecraft:water_bucket":473,"minecraft:soul_sand":9,"minecraft:cyan_bed":2,"minecraft:netherite_boots":2,"minecraft:netherite_leggings":6,"minecraft:bread":56,"minecraft:torch":41,"minecraft:jungle_sapling":185,"minecraft:lever":5,"minecraft:deepslate_redstone_ore":2,"minecraft:polished_blackstone_bricks":84,"minecraft:tripwire_hook":36,"minecraft:cobblestone_slab":63,"minecraft:cobweb":182,"minecraft:gravel":35,"minecraft:green_bed":1,"minecraft:cake":1,"minecraft:composter":10,"minecraft:jungle_leaves":10,"minecraft:smooth_sandstone":2,"minecraft:ender_chest":110,"minecraft:flint_and_steel":2,"minecraft:redstone_torch":1,"minecraft:warped_trapdoor":5,"minecraft:chest":38,"minecraft:brown_bed":3,"minecraft:sandstone":76,"minecraft:ender_pearl":531}},"DataVersion":4440}